fatpy/__init__.py
fatpy/_version.py
fatpy/core/__init__.py
fatpy/core/energy_life/__init__.py
fatpy/core/energy_life/base_methods.py
fatpy/core/energy_life/correction_methods.py
fatpy/core/energy_life/decompositions.py
fatpy/core/energy_life/demage_parameters.py
fatpy/core/strain_life/__init__.py
fatpy/core/strain_life/base_methods.py
fatpy/core/strain_life/correction_methods.py
fatpy/core/strain_life/decompositions.py
fatpy/core/strain_life/demage_parameters.py
fatpy/core/stress_life/__init__.py
fatpy/core/stress_life/base_methods.py
fatpy/core/stress_life/correction_methods.py
fatpy/core/stress_life/decompositions.py
fatpy/core/stress_life/demage_parameters.py
fatpy/data_parsing/__init__.py
fatpy/data_parsing/fe_model.py
fatpy/data_parsing/loads.py
fatpy/data_parsing/material.py
fatpy/data_parsing/user_input.py
fatpy/utilities/__init__.py
fatpy/utilities/post_processing.py
fatpy/utilities/pre_processing.py
fatpy/utilities/transformation.py
fatpy-0.1.1.dist-info/licenses/LICENSE.md
fatpy-0.1.1.dist-info/METADATA
fatpy-0.1.1.dist-info/WHEEL
fatpy-0.1.1.dist-info/top_level.txt
fatpy-0.1.1.dist-info/RECORD
