Metadata-Version: 2.4
Name: FatPy
Version: 0.1.1
Summary: Python implementations of various life algorithms
Author-email: Jan Vyborny <jan.vyborny2@gmail.com>
License: MIT
Project-URL: Homepage, https://github.com/vybornak2/FatPy
Project-URL: Bug Tracker, https://github.com/vybornak2/FatPy/issues
Project-URL: Documentation, https://vybornak2.github.io/FatPy/
Project-URL: FABER, https://faber-cost.eu/
Project-URL: LinkedIn, https://www.linkedin.com/company/faber-cost/about/
Classifier: Development Status :: 3 - Alpha
Classifier: Intended Audience :: Science/Research
Classifier: License :: OSI Approved :: MIT License
Classifier: Programming Language :: Python :: 3
Classifier: Programming Language :: Python :: 3.12
Classifier: Topic :: Scientific/Engineering
Classifier: Topic :: Scientific/Engineering :: Physics
Requires-Python: >=3.12
License-File: LICENSE.md
Requires-Dist: matplotlib>=3.10.0
Requires-Dist: numpy>=2.2.2
Requires-Dist: pandas>=2.2.3
Requires-Dist: scipy>=1.15.1
Dynamic: license-file
